{"old_nid":"13658721","title":"Best Drill for Anti-Slice Release","video_id":"2581666151001","video_duration":"190799","update_brightcove":"0","brightcove_name":"Best Drill for Anti-Slice Release","brightcove_short_desc":"Best Drill for Anti-Slice Release","brightcove_long_desc":null,"brightcove_related_text":"Best Drill for Anti-Slice Release, by Mike Bender","brightcove_related_url":"http:\/\/www.golf.com\/video\/best-drill-anti-slice-release","brightcove_tags":"special_feature","brightcove_images":"http:\/\/i.cdn.turner.com\/dr\/golf\/www\/release\/sites\/default\/files\/Best\nhttp:\/\/timeInc.brightcove.com.edgesuite.net\/rtmp_uds\/416418725\/416418725_2581665550001_9313-1375393599-43797-thumbnail-287941763-thumbnail.jpg?pubId=416418725","brightcove_reference_id":"278393","brightcove_category":"Instruction","brightcove_subcategory":"","brightcove_ad_tag":"","brightcove_first_published":"","brightcove_edit_source":"","brightcove_syndicate":"1","brightcove_url":"","brightcove_event":"","brightcove_game_id":"","brightcove_ramp_state":"HTX","brightcove_ramp_keywords":"Mike Bender,Golf Magazine","brightcove_ramp_guid":"","headline":"Best Drill for Anti-Slice Release","description":null,"short_headline":"Best Drill for Anti-Slice Release","page_title":"Best Drill for Anti-Slice Release, by Mike Bender","slug":"Best Drill for Anti-Slice Release","category_term":"9048","category_name":"News","subcategory_term":null,"subcategory":null,"video_source_name":null,"video_type":"Video","video":{"brightcove_id":"2581666151001","player":"video"},"video_show_state":null,"video_show_name":null,"video_episode":null,"body":"Best Drill for Anti-Slice Release","images_ref":"13590853","tags":[],"ad_tags":[],"caption":"","credit":"","transcript":null,"deck":null,"legacy_id":"278393","eyebrow":null,"player_id":"","publish_date":"2014-11-12 21:28:28","updated_date":"2014-12-05 19:46:00","syndication":"1","not_searchable":"0","comments":null,"url_alias":"video\/best-drill-anti-slice-release"}